pybase_ext/__init__.py
pybase_ext/_version.py
pybase_ext/colors/__init__.py
pybase_ext/constants/__init__.py
pybase_ext/constants/_generate_color_enums.py
pybase_ext/constants/colors.py
pybase_ext/enum/__init__.py
pybase_ext/enum/_types.py
pybase_ext-0.1.2.dist-info/LICENSE
pybase_ext-0.1.2.dist-info/METADATA
pybase_ext-0.1.2.dist-info/WHEEL
pybase_ext-0.1.2.dist-info/top_level.txt
pybase_ext-0.1.2.dist-info/RECORD
