Metadata-Version: 2.1
Name: pybase-ext
Version: 0.1.2
Summary: Python package to backport classes from new python releases (for example,
Author-email: Jaime Gonzalez Gomez <jim.gomez.dnn@gmail.com>
License: MIT license
Project-URL: Source, https://github.com/Jtachan/PyBaseExtension.git
Requires-Python: >=3.8
License-File: LICENSE
